{
  "translation": {
    "app_title": "Title",
    "Current delivery and pick-up times": "Aktuelle Liefer- und Abholzeiten",
    "Categories": "Kategorien",
    "About Us": "Über Uns",
    "Contact Us": "Kontakt",
    "Offers": "Angebote",
    "Privacy Policy": "Datenschutzerklärung",
    "Terms & Conditions": "AGB's",
    "Total": "Insgesamt",
    "items Found": "Produkte gefunden",
    "Get Your Food From Our Vedis Restaurant": "Holen Sie sich Ihr Essen von unserem Vedis Restaurant",
    "There are many offer on the App.": "Es gibt viele Angebote in der App.",
    "Copyright 2022 © Vedis ": "Copyright 2022 © Vedis ",
    "Search for products(eg fish ,Chicken)": "Suche nach Produkten (z.B. Fisch, Huhn)",
    "You must have an order with a minimum of": "Sie müssen einen Mindestbestellwert von",
    "to place your order. Your current order total is": "haben, um Ihre Bestellung aufzugeben. Ihr aktueller Bestellwert beträgt",
    "Cart Page": "Warenkorb",
    "Item": "Produkt",
    "Items": "Produkte",
    "Your cart is empty": "Ihr Warenkorb ist leer",
    "No items added in your cart. Please add product to your cart list.": "Keine Artikel in Ihrem Warenkorb hinzugefügt. Bitte fügen Sie das Produkt Ihrer Warenkorbliste hinzu.",
    "Item Price": "Produktpreis",
    "Shopping Cart": "Warenkorb",
    "Add To Cart": "In den Warenkorb legen",
    "Close": "Schließen",
    "Proceed To Checkout": "Zur Kasse gehen",
    "Personal Details": "Persönliche Daten",
    "Please select/fill the address": "Bitte wählen/füllen Sie die Adresse aus",
    "No Item Added Yet!": "Noch kein Artikel hinzugefügt!",
    "First Name": "Vornameam",
    "Input Your Coupon code": "Geben Sie Ihren Gutscheincode ein",
    "Last name": "Nachname",
    "Email address": "E-Mail Adresse",
    "Email Address": "E-Mail Adresse",
    "Phone number": "Telefonnummer",
    "Shipping Details": "Versandinformationen",
    "City": "Stadt",
    "Country": "Land",
    "Postal": "PLZ",
    "Payment Details": "Zahlungsinformationen",
    "Cash On Delivery": "Nachnahme",
    "Credit Card": "Kreditkarte",
    "Paypal": "PayPal",
    "Continue Shopping": "Weiter einkaufen",
    "Confirm Order": "Bestellung bestätigen",
    "Delivery service is currently unavailable.": "Der Lieferservice ist derzeit nicht verfügbar.",
    "Order Summary": "Zusammenfassung der Bestellung",
    "Subtotal": "Zwischensumme",
    "Discount": "Rabatt",
    "Total cost": "GESAMTKOSTEN",
    "Apply": "Anwenden",
    "Delivery": "Lieferung",
    "Pickup": "Abholung",
    "Dashboard": "Dashboard",
    "My Orders": "Meine Bestellungen",
    "Profile": "Profil",
    "Logout": "Abmelden",
    "Full Name": "Vollständiger Name",
    "Recent Order": "Aktuelle Bestellung",
    "Your Address": "Ihre Adresse",
    "OrderTime": "BESTELLZEIT",
    "Mobile": "Handynummer",
    "Method": "METHODE",
    "Check delivery area": "Liefergebiet prüfen",
    "Enter address": "Adresse eingeben",
    "TOTAL": "GESAMT",
    "Details": "Einzelheiten",
    "Thank you ! Your order have been received !": "Vielen Dank! Ihre Bestellung ist eingegangen!",
    "INVOICE": "RECHNUNG",
    "Unfortunately, delivery to your address is currently not possible": "Eine Lieferung an Ihre Adresse ist derzeit leider nicht möglich",
    "Delivery to your address is possible": "Eine Lieferung an Ihre Adresse ist möglich",
    "INVOICE To": "RECHNUNG an",
    "invoice Number": "Rechnungsnummer",
    "Date": "Datum",
    "PRODUCT NAME": "PRODUKTNAME",
    "QUANTITY": "ANZAHL",
    "AMOUNT": "BETRAG",
    "PAYMENT METHOD": "ZAHLUNGSART",
    "SHIPPING COST": "VERSANDKOSTEN",
    "TOTAL AMOUNT": "GESAMTBETRAG",
    "Home": "Startseite",
    "contains cereals containing gluten (wheat, rye, barley, oats, spelt, etc.).": "enthält glutenhaltige Getreide (Weizen, Roggen, Gerste, Hafer, Dinkel usw.).",
    "contains crustaceans or crustacean products.": "enthält Krebstiere oder Krebstier-Erzeugnisse.",
    "contains eggs or egg products.": "enthält Eier oder Ei-Erzeugnisse.",
    "contains fish or fish products.": "enthält Fisch oder Fischerzeugnisse.",
    "contains peanuts or peanut products.": "enthält Erdnüsse oder Erdnusserzeugnisse.",
    "contains soy or soy products.": "enthält Soja oder Sojaerzeugnisse.",
    "contains milk or milk products (lactose).": "enthält Milch oder Milcherzeugnisse (Laktose).",
    "contains nuts or their products (almonds, hazelnuts, walnuts, cashew nuts, pecan nuts, Brazil nuts, pistachio nuts, macadamia nuts, Quenland nuts).": "enthält Schalenfrüchte oder deren Erzeugnisse (Mandel, Haselnuss, Walnuss, Cashewnuss, Pecanuss, Paranuss, Pistazie, Macadamianuss, Quenlandnuss).",
    "contains celery or celery products.": "enthält Sellerie oder Sellerieerzeugnisse.",
    "contains mustard or mustard products.": "enthält Senf oder Senferzeugnisse.",
    "contains sesame seeds or sesame seed products.": "enthält Sesamsamen oder Sesamsamenerzeugnisse.",
    "contains sulfur dioxide and sulphites.": "enthält Schwefeldioxid und Sulfite.",
    "contains lupine or products thereof.": "enthält Lupine oder Erzeugnisse daraus.",
    "contains mollusks or products made from them.": "enthält Weichtiere(Moluslen) oder Erzeugnisse daraus.",
    "flavor enhancer, with coloring, pixelio.delkm ": "Geschmacksverstärker, mit Farbstoff, pixelio.delkm",
    "caffeine-based,": "Koffeinhaltig,",
    "quinine-based,": "chininhaltig,",
    "with antioxidants,": "mit Antioxidationsmitteln,",
    "with sweeteners (contains a source of phenylalanine),": " mit Süßungsmitteln (enthält eine Phenylalaninquelle)",
    "acidulants,": " Säuerungsmittel",
    "stabilizers": " Stabilisatoren",
    "Indian delivery service - order Indian now !":"Indischer Lieferservice - jetzt indisch bestellen!"
  }
}